package/__init__.py
package/cons_var_term.py
package/main.py
package/minmax_term.py
package/solver.py
solveminmax/__init__.py
solveminmax/cons_var_term.py
solveminmax/main.py
solveminmax/minmax_term.py
solveminmax/solver.py
solveminmax-0.1.3.dist-info/LICENSE
solveminmax-0.1.3.dist-info/METADATA
solveminmax-0.1.3.dist-info/WHEEL
solveminmax-0.1.3.dist-info/top_level.txt
solveminmax-0.1.3.dist-info/RECORD
